ipycpp/__init__.py
ipycpp/__main__.py
ipycpp-0.0.6.data/data/share/jupyter/kernels/ipycpp/kernel.json
ipycpp-0.0.6.dist-info/METADATA
ipycpp-0.0.6.dist-info/WHEEL
ipycpp-0.0.6.dist-info/licenses/LICENSE
ipycpp-0.0.6.dist-info/RECORD
