Metadata-Version: 2.1
Name: ipycpp
Version: 0.0.6
Summary: Simple jupyter kernel for C++ (cpp, cplusplus) in pure python!
Project-URL: Homepage, https://github.com/lucafabbian/ipycpp
Project-URL: Bug Tracker, https://github.com/lucafabbian/ipycpp/issues
Author-email: Luca Fabbian <luca.fabbian.1999@gmail.com>
License-File: LICENSE
Classifier: License :: OSI Approved :: MIT License
Classifier: Operating System :: OS Independent
Classifier: Programming Language :: Python :: 3
Requires-Python: >=3.6
Requires-Dist: ipykernel>=6
